terraform_var_manager/__init__.py
terraform_var_manager/api_client.py
terraform_var_manager/main.py
terraform_var_manager/py.typed
terraform_var_manager/utils.py
terraform_var_manager/variable_manager.py
terraform_var_manager-1.0.1.dist-info/WHEEL
terraform_var_manager-1.0.1.dist-info/entry_points.txt
terraform_var_manager-1.0.1.dist-info/METADATA
terraform_var_manager-1.0.1.dist-info/RECORD
