Metadata-Version: 2.3
Name: terraform-var-manager
Version: 1.0.1
Summary: A tool to manage Terraform Cloud variables with advanced features like comparison, synchronization, and tagging
Keywords: terraform,terraform-cloud,variables,devops,infrastructure
Author: Geordy Kindley
Author-email: Geordy Kindley <gekindley@gmail.com>
License: MIT License
Classifier: Development Status :: 5 - Production/Stable
Classifier: Intended Audience :: Developers
Classifier: Intended Audience :: System Administrators
Classifier: License :: OSI Approved :: MIT License
Classifier: Operating System :: OS Independent
Classifier: Programming Language :: Python :: 3
Classifier: Programming Language :: Python :: 3.9
Classifier: Programming Language :: Python :: 3.10
Classifier: Programming Language :: Python :: 3.11
Classifier: Programming Language :: Python :: 3.12
Classifier: Topic :: Software Development :: Build Tools
Classifier: Topic :: System :: Systems Administration
Requires-Dist: requests>=2.28.0
Requires-Python: >=3.9
Project-URL: Documentation, https://github.com/gekindley/terraform-var-manager#readme
Project-URL: Homepage, https://github.com/gekindley/terraform-var-manager
Project-URL: Issues, https://github.com/gekindley/terraform-var-manager/issues
Project-URL: Repository, https://github.com/gekindley/terraform-var-manager
